atqdm/__init__.py
atqdm-0.0.7.dist-info/LICENSE
atqdm-0.0.7.dist-info/METADATA
atqdm-0.0.7.dist-info/WHEEL
atqdm-0.0.7.dist-info/top_level.txt
atqdm-0.0.7.dist-info/RECORD
