Metadata-Version: 2.1
Name: atqdm
Version: 0.0.7
Summary: Tqdm replacement for Comet / W&B reporting
Author-email: Sergey Skrebnev <sergey.skrebnev@gmail.com>
Project-URL: Homepage, https://github.com/skrbnv/atqdm
Classifier: Programming Language :: Python :: 3
Classifier: License :: OSI Approved :: Apache Software License
Classifier: Operating System :: OS Independent
Requires-Python: >=3.0
License-File: LICENSE
